rogi/__init__.py
rogi/_version.py
rogi/modi.py
rogi/roughness_index.py
rogi/sari.py
rogi-0.1.dist-info/LICENSE
rogi-0.1.dist-info/METADATA
rogi-0.1.dist-info/WHEEL
rogi-0.1.dist-info/top_level.txt
rogi-0.1.dist-info/RECORD
