Metadata-Version: 2.1
Name: rogi
Version: 0.1
Summary: Measures of roughness for molecular property landscapes
Home-page: https://github.com/coleygroup/rogi
Author: Matteo Aldeghi
Author-email: maldeghi@mit.edu
License: MIT
Classifier: Development Status :: 3 - Alpha
Classifier: License :: OSI Approved :: MIT License
Classifier: Programming Language :: Python
Classifier: Intended Audience :: Science/Research
Classifier: Topic :: Scientific/Engineering
Requires-Python: >=3.7
License-File: LICENSE
Requires-Dist: numpy
Requires-Dist: scipy (>=1.4)
Requires-Dist: fastcluster
Requires-Dist: pandas
Requires-Dist: scikit-learn (>=1)
